sciduck/__init__.py
sciduck/annotation_table.py
sciduck/basic_qc.py
sciduck/entropy_qc.py
sciduck/plotting.py
sciduck/templates.py
sciduck-0.5.5.dist-info/METADATA
sciduck-0.5.5.dist-info/WHEEL
sciduck-0.5.5.dist-info/RECORD
